Poggers/__init__.py
poggers-0.0.6.dist-info/LICENSE.txt
poggers-0.0.6.dist-info/METADATA
poggers-0.0.6.dist-info/WHEEL
poggers-0.0.6.dist-info/top_level.txt
poggers-0.0.6.dist-info/RECORD
