Metadata-Version: 2.1
Name: poggers
Version: 0.0.6
Summary: A small package for converting text to ascii
Home-page: https://google.com
Author: Rika
Author-email: jayden05jaydenhigginsjayden05@hotmail.com
License: UNKNOWN
Platform: UNKNOWN
Classifier: Programming Language :: Python :: 3
Classifier: License :: OSI Approved :: MIT License
Classifier: Operating System :: OS Independent
Requires-Python: >=3.6
